Metadata-Version: 1.0
Name: dimas-distributions
Version: 0.1
Summary: Gaussian distribution and Binomial Distributions
Home-page: UNKNOWN
Author: Dimas Torres
Author-email: UNKNOWN
License: UNKNOWN
Platform: UNKNOWN
